asgi.py
workers/__init__.py
workers/_workers.py
workers/py.typed
workers/workflows.py
workers_runtime_sdk-0.3.1.dist-info/METADATA
workers_runtime_sdk-0.3.1.dist-info/WHEEL
workers_runtime_sdk-0.3.1.dist-info/RECORD
