Metadata-Version: 2.4
Name: workers-runtime-sdk
Version: 0.3.1
Summary: Python runtime SDK for Cloudflare Workers
Requires-Python: >=3.12
